{"__type__":"sp.SkeletonData","_name":"jiazhai","_rawFiles":["raw-skeleton.json"],"_skeletonJson":{"skeleton":{"hash":"gbQFNLO1jePyuAQtcaJ0kn4SFgg","spine":"3.7.94","width":2340,"height":1080},"bones":[{"name":"root"},{"name":"zunbei","parent":"root"}],"slots":[{"name":"bg","bone":"root"},{"name":"zunbei","bone":"zunbei","attachment":"zunbei"}],"skins":{"default":{"zunbei":{"zunbei":{"scaleX":0.591,"scaleY":0.591,"width":336,"height":336}}}},"animations":{"animation":{"slots":{"zunbei":{"color":[{"time":0,"color":"ffffffff"},{"time":1,"color":"ffffffa8"},{"time":2,"color":"ffffffff"}]}},"bones":{"zunbei":{"rotate":[{"time":0,"angle":0},{"time":0.5,"angle":-90},{"time":1,"angle":-180},{"time":1.5,"angle":90},{"time":2,"angle":0}]}}}}},"_atlasText":"\r\njiazhai.png\r\nsize: 512,512\r\nformat: RGBA8888\r\nfilter: Linear,Linear\r\nrepeat: none\r\nzunbei\r\n  rotate: false\r\n  xy: 2, 2\r\n  size: 336, 336\r\n  orig: 336, 336\r\n  offset: 0, 0\r\n  index: -1\r\n","atlasUrl":{"__uuid__":"ddFnN3SsVIJa+BDhnTg3fi"},"textures":[{"__uuid__":"eb3YAhzaBK3Ys/MZGyOBAj"}]}