[{"__type__":"cc.Prefab","_name":"Fish16","data":{"__id__":1},"asyncLoadAssets":null},{"__type__":"cc.Node","_name":"Fish16","_components":[{"__type__":"cc.Sprite","node":{"__id__":1},"_spriteFrame":{"__uuid__":"ffErWwStpB5JGwvLjgIMO5"},"_sizeMode":2,"_isTrimmedMode":false},{"__type__":"78ddcWG2t9IK4VFyVu7v/Ns","node":{"__id__":1},"nodeFish":{"__id__":1}},{"__type__":"cc.Animation","node":{"__id__":1},"_defaultClip":{"__uuid__":"56fdxxzFVDSK65wT8otWqM"},"_clips":[{"__uuid__":"56fdxxzFVDSK65wT8otWqM"}],"playOnLoad":true},{"__type__":"cc.BoxCollider","node":{"__id__":1},"_offset":{"__type__":"cc.Vec2","x":1.7,"y":30.5},"_size":{"__type__":"cc.Size","width":124.6,"height":99.5}}],"_prefab":{"__type__":"cc.PrefabInfo","root":{"__id__":1},"asset":{"__id__":0},"fileId":"75orRun2dOZp11AcE/pfhR"},"_contentSize":{"__type__":"cc.Size","width":131,"height":203},"_scaleX":1.5,"_scaleY":1.5,"groupIndex":1}]