{"__type__":"sp.SkeletonData","_name":"lightning","_rawFiles":["raw-skeleton.json"],"_skeletonJson":{"skeleton":{"hash":"RCSNFgtKcGsvjskWuRexV+D9Im4","spine":"3.7.94","width":482.4,"height":262.08},"bones":[{"name":"root"},{"name":"fight_sd_00000","parent":"root"}],"slots":[{"name":"fight_sd_00000","bone":"fight_sd_00000","attachment":"fight_sd_00011","blend":"additive"}],"skins":{"default":{"fight_sd_00000":{"fight_sd_00000":{"scaleX":1.44,"scaleY":1.44,"width":335,"height":182},"fight_sd_00001":{"scaleX":1.44,"scaleY":1.44,"width":335,"height":182},"fight_sd_00002":{"scaleX":1.44,"scaleY":1.44,"width":335,"height":182},"fight_sd_00003":{"scaleX":1.44,"scaleY":1.44,"width":335,"height":182},"fight_sd_00004":{"scaleX":1.44,"scaleY":1.44,"width":335,"height":182},"fight_sd_00005":{"scaleX":1.44,"scaleY":1.44,"width":335,"height":182},"fight_sd_00006":{"scaleX":1.44,"scaleY":1.44,"width":335,"height":182},"fight_sd_00007":{"scaleX":1.44,"scaleY":1.44,"width":335,"height":182},"fight_sd_00008":{"scaleX":1.44,"scaleY":1.44,"width":335,"height":182},"fight_sd_00009":{"scaleX":1.44,"scaleY":1.44,"width":335,"height":182},"fight_sd_00010":{"scaleX":1.44,"scaleY":1.44,"width":335,"height":182},"fight_sd_00011":{"scaleX":1.44,"scaleY":1.44,"width":335,"height":182}}}},"animations":{"animation":{"slots":{"fight_sd_00000":{"attachment":[{"time":0,"name":"fight_sd_00000"},{"time":0.1667,"name":"fight_sd_00001"},{"time":0.3333,"name":"fight_sd_00002"},{"time":0.5,"name":"fight_sd_00003"},{"time":0.6667,"name":"fight_sd_00004"},{"time":0.8333,"name":"fight_sd_00005"},{"time":1,"name":"fight_sd_00006"},{"time":1.1667,"name":"fight_sd_00007"},{"time":1.3333,"name":"fight_sd_00008"},{"time":1.5,"name":"fight_sd_00009"},{"time":1.6667,"name":"fight_sd_00010"},{"time":1.8333,"name":"fight_sd_00011"},{"time":2,"name":null}]}}}}},"_atlasText":"\r\nlightning.png\r\nsize: 2048,512\r\nformat: RGBA8888\r\nfilter: Linear,Linear\r\nrepeat: none\r\nfight_sd_00000\r\n  rotate: false\r\n  xy: 2, 150\r\n  size: 268, 146\r\n  orig: 268, 146\r\n  offset: 0, 0\r\n  index: -1\r\nfight_sd_00001\r\n  rotate: false\r\n  xy: 272, 298\r\n  size: 268, 146\r\n  orig: 268, 146\r\n  offset: 0, 0\r\n  index: -1\r\nfight_sd_00002\r\n  rotate: false\r\n  xy: 2, 2\r\n  size: 268, 146\r\n  orig: 268, 146\r\n  offset: 0, 0\r\n  index: -1\r\nfight_sd_00003\r\n  rotate: false\r\n  xy: 272, 150\r\n  size: 268, 146\r\n  orig: 268, 146\r\n  offset: 0, 0\r\n  index: -1\r\nfight_sd_00004\r\n  rotate: false\r\n  xy: 542, 298\r\n  size: 268, 146\r\n  orig: 268, 146\r\n  offset: 0, 0\r\n  index: -1\r\nfight_sd_00005\r\n  rotate: false\r\n  xy: 272, 2\r\n  size: 268, 146\r\n  orig: 268, 146\r\n  offset: 0, 0\r\n  index: -1\r\nfight_sd_00006\r\n  rotate: false\r\n  xy: 542, 150\r\n  size: 268, 146\r\n  orig: 268, 146\r\n  offset: 0, 0\r\n  index: -1\r\nfight_sd_00007\r\n  rotate: false\r\n  xy: 812, 298\r\n  size: 268, 146\r\n  orig: 268, 146\r\n  offset: 0, 0\r\n  index: -1\r\nfight_sd_00008\r\n  rotate: false\r\n  xy: 542, 2\r\n  size: 268, 146\r\n  orig: 268, 146\r\n  offset: 0, 0\r\n  index: -1\r\nfight_sd_00009\r\n  rotate: false\r\n  xy: 812, 150\r\n  size: 268, 146\r\n  orig: 268, 146\r\n  offset: 0, 0\r\n  index: -1\r\nfight_sd_00010\r\n  rotate: false\r\n  xy: 1082, 298\r\n  size: 268, 146\r\n  orig: 268, 146\r\n  offset: 0, 0\r\n  index: -1\r\nfight_sd_00011\r\n  rotate: false\r\n  xy: 2, 298\r\n  size: 268, 146\r\n  orig: 268, 146\r\n  offset: 0, 0\r\n  index: -1\r\n","atlasUrl":{"__uuid__":"0eQkP2YZRHdLaXYoGwoAV+"},"textures":[{"__uuid__":"detP3lR/NCn649jiaaa+P8"}]}