{"__type__":"sp.SkeletonData","_name":"bet","_rawFiles":["raw-skeleton.json"],"_skeletonJson":{"skeleton":{"hash":"UeTw0i1Tku9Ru0mhIFb0tqIDfNE","spine":"3.7.94","width":1546.15,"height":205.12,"images":"","audio":""},"bones":[{"name":"root"},{"name":"startbetting","parent":"root"}],"slots":[{"name":"startbetting","bone":"startbetting","color":"ffffff00","attachment":"stopbetting"}],"skins":{"default":{"startbetting":{"startbetting":{"rotation":0.04,"width":1546,"height":204},"stopbetting":{"rotation":0.04,"width":1546,"height":204}}}},"animations":{"star":{"slots":{"startbetting":{"color":[{"time":0,"color":"ffffff00","curve":[0.25,0,0.75,1]},{"time":0.3333,"color":"ffffffff","curve":"stepped"},{"time":1.3333,"color":"ffffffff","curve":[0.25,0,0.75,1]},{"time":1.6667,"color":"ffffff00"}],"attachment":[{"time":0,"name":"startbetting"}]}}},"stop":{"slots":{"startbetting":{"color":[{"time":0,"color":"ffffff00","curve":[0.25,0,0.75,1]},{"time":0.3333,"color":"ffffffff","curve":"stepped"},{"time":1.3333,"color":"ffffffff","curve":[0.25,0,0.75,1]},{"time":1.6667,"color":"ffffff00"}],"attachment":[{"time":0,"name":"stopbetting"}]}}}}},"_atlasText":"\r\nbet.png\r\nsize: 2048,512\r\nformat: RGBA8888\r\nfilter: Linear,Linear\r\nrepeat: none\r\nstartbetting\r\n  rotate: false\r\n  xy: 2, 2\r\n  size: 1546, 204\r\n  orig: 1546, 204\r\n  offset: 0, 0\r\n  index: -1\r\nstopbetting\r\n  rotate: false\r\n  xy: 2, 208\r\n  size: 1546, 204\r\n  orig: 1546, 204\r\n  offset: 0, 0\r\n  index: -1\r\n","atlasUrl":{"__uuid__":"9aY55/ytdOgrO6QkhePAu4"},"textures":[{"__uuid__":"ccspiT/m1P9oenSv52yLId"}]}