{"__type__":"sp.SkeletonData","_name":"line_43","_rawFiles":["raw-skeleton.json"],"_skeletonJson":{"skeleton":{"hash":"sb+EP84gwi9blzpDnDdlBAf7K7E","spine":"3.7.94","width":1920,"height":1080,"images":"","audio":"C:/Users/USER/Desktop/线动画"},"bones":[{"name":"root"},{"name":"bg","parent":"root"},{"name":"bone43","parent":"root","y":100.94,"scaleX":2,"scaleY":2}],"slots":[{"name":"images/bg","bone":"bg"},{"name":"images/43","bone":"bone43","color":"ffffff00","attachment":"images/43","blend":"additive"}],"skins":{"default":{"images/43":{"images/43":{"width":679,"height":198}}}},"animations":{"animation":{"slots":{"images/43":{"color":[{"time":0,"color":"ffffff00"},{"time":0.3667,"color":"ffffffff"},{"time":0.6667,"color":"ffffff00"},{"time":1.0333,"color":"ffffffff"},{"time":1.3333,"color":"ffffff00"}]}}}}},"_atlasText":"\r\nline_43.png\r\nsize: 512,256\r\nformat: RGBA8888\r\nfilter: Linear,Linear\r\nrepeat: none\r\nimages/43\r\n  rotate: false\r\n  xy: 2, 2\r\n  size: 489, 143\r\n  orig: 489, 143\r\n  offset: 0, 0\r\n  index: -1\r\n","atlasUrl":{"__uuid__":"7arbCMCzVK6pTeswX15qIB"},"textures":[{"__uuid__":"f0oTurU+lNQ7Qq7shHwbtR"}]}