[{"__type__":"cc.Prefab","_name":"pfSubPayItem","data":{"__id__":1},"asyncLoadAssets":null},{"__type__":"cc.Node","_name":"pfSubPayItem","_children":[{"__id__":2},{"__id__":3}],"_components":[{"__type__":"cc.Sprite","node":{"__id__":1},"_spriteFrame":{"__uuid__":"92lsJK62RGqKKCVcWyvUck"}},{"__type__":"cc.Button","node":{"__id__":1},"_N$target":{"__id__":1}}],"_prefab":{"__type__":"cc.PrefabInfo","root":{"__id__":1},"asset":{"__uuid__":"07/rlMpxdKupQ/tNxjgvIv"},"fileId":"424lCpc5pLZYOM/scBFslv"},"_contentSize":{"__type__":"cc.Size","width":172,"height":61},"_scaleX":1.2,"_scaleY":1.2},{"__type__":"cc.Node","_name":"graysprite","_parent":{"__id__":1},"_components":[{"__type__":"cc.Sprite","node":{"__id__":2},"_spriteFrame":{"__uuid__":"29AyauwktNp5vxdupvXd1E"}}],"_prefab":{"__type__":"cc.PrefabInfo","root":{"__id__":1},"asset":{"__uuid__":"07/rlMpxdKupQ/tNxjgvIv"},"fileId":"1aS6ir6wlL9rQfpHwOyxbv"},"_contentSize":{"__type__":"cc.Size","width":172,"height":64}},{"__type__":"cc.Node","_name":"channel","_parent":{"__id__":1},"_components":[{"__type__":"cc.Label","node":{"__id__":3},"_useOriginalSize":false,"_actualFontSize":32,"_fontSize":32,"_lineHeight":42,"_N$string":"GCash1"}],"_prefab":{"__type__":"cc.PrefabInfo","root":{"__id__":1},"asset":{"__uuid__":"07/rlMpxdKupQ/tNxjgvIv"},"fileId":"3bZQhwAudPDZ7FmuO932jZ"},"_color":{"__type__":"cc.Color","r":157,"g":90,"b":2},"_contentSize":{"__type__":"cc.Size","width":117.39,"height":42}}]